proxyctx/__init__.py
proxyctx/_version.py
proxyctx/context.py
proxyctx/proxy.py
proxyctx-0.1.1.dist-info/LICENSE
proxyctx-0.1.1.dist-info/METADATA
proxyctx-0.1.1.dist-info/WHEEL
proxyctx-0.1.1.dist-info/top_level.txt
proxyctx-0.1.1.dist-info/RECORD
