Metadata-Version: 2.1
Name: proxyctx
Version: 0.1.1
Summary: ProxyCTX is a utility library for global context inspired by Flask, leveraging contextvars
Author-email: Lucino772 <lucapalmi772@gmail.com>
License: MIT
Project-URL: Homepage, https://github.com/Lucino772/proxyctx
Project-URL: Changelog, https://github.com/Lucino772/proxyctx/blob/main/CHANGELOG.rst
Classifier: License :: OSI Approved :: MIT License
Classifier: Operating System :: OS Independent
Classifier: Programming Language :: Python :: 3.7
Classifier: Programming Language :: Python :: 3.8
Classifier: Programming Language :: Python :: 3.9
Requires-Python: >=3.7
License-File: LICENSE
